rho_plus/__init__.py
rho_plus/_scatter_label.py
rho_plus/bokeh.py
rho_plus/color_util.py
rho_plus/colors.py
rho_plus/data/__init__.py
rho_plus/data/fonts/SourceSans3-Bold.ttf
rho_plus/data/fonts/SourceSans3-Regular.ttf
rho_plus/data/plotly_rho_dark.json
rho_plus/data/plotly_rho_light.json
rho_plus/data/sequential_palettes.json
rho_plus/data/vega_rho_dark.json
rho_plus/data/vega_rho_light.json
rho_plus/fonts.py
rho_plus/matplotlib.py
rho_plus/matplotlib_tweaks.py
rho_plus/oklch_palettes.py
rho_plus/palettes.py
rho_plus/panel.py
rho_plus/plotly.py
rho_plus/sequential_palettes.py
rho_plus/smoothing.py
rho_plus/util.py
rho_plus/vega.py
rho_plus-0.6.0.dist-info/METADATA
rho_plus-0.6.0.dist-info/WHEEL
rho_plus-0.6.0.dist-info/RECORD
