Metadata-Version: 2.1
Name: rho_plus
Version: 0.6.0
Summary: The Python data viz nitro canister you didn't know you needed
License: MIT
Author: Nicholas Miklaucic
Author-email: nicholas.miklaucic@gmail.com
Requires-Python: >=3.8,<=3.12
Classifier: License :: OSI Approved :: MIT License
Classifier: Programming Language :: Python :: 3
Classifier: Programming Language :: Python :: 3.8
Classifier: Programming Language :: Python :: 3.9
Classifier: Programming Language :: Python :: 3.10
Classifier: Programming Language :: Python :: 3.11
Classifier: Programming Language :: Python :: 3.12
Provides-Extra: dev
Requires-Dist: colour-science (==0.4.1) ; (python_version >= "3.8" and python_version < "3.9") and (extra == "dev")
Requires-Dist: colour-science (==0.4.2) ; (python_version >= "3.9" and python_full_version <= "3.11.0") and (extra == "dev")
Requires-Dist: hsluv (>=5.0.3,<6.0.0)
Requires-Dist: matplotlib (>=3,<4) ; extra == "dev"
Requires-Dist: numpy (>=1.21)
Requires-Dist: scipy (>=1.7.0) ; extra == "dev"
Requires-Dist: seaborn (>=0.11) ; extra == "dev"
